composite_field/__init__.py
composite_field/base.py
composite_field/complex.py
composite_field/l10n.py
composite_field/models.py
composite_field/rest_framework_support.py
composite_field/tests.py
django_composite_field-2.0.1.dist-info/AUTHORS
django_composite_field-2.0.1.dist-info/LICENSE-APACHE
django_composite_field-2.0.1.dist-info/LICENSE-BSD
django_composite_field-2.0.1.dist-info/LICENSE-MIT
django_composite_field-2.0.1.dist-info/METADATA
django_composite_field-2.0.1.dist-info/WHEEL
django_composite_field-2.0.1.dist-info/RECORD
